PhantomBrowser/AsyncBrowser.py
PhantomBrowser/Browser.py
PhantomBrowser/__init__.py
PhantomBrowser/py.typed
phantombrowser-0.0.4.data/scripts/phantomdl
phantombrowser-0.0.4.dist-info/LICENSE
phantombrowser-0.0.4.dist-info/METADATA
phantombrowser-0.0.4.dist-info/WHEEL
phantombrowser-0.0.4.dist-info/top_level.txt
phantombrowser-0.0.4.dist-info/RECORD
