Metadata-Version: 2.1
Name: phantombrowser
Version: 0.0.4
Summary: Typed Python wrapper for Phantomjs Cloud API
Home-page: https://github.com/guangrei/PhantomBrowser
Author: guangrei
Author-email: myawn@pm.me
License: MIT
Platform: any
License-File: LICENSE
Requires-Dist: types-aiofiles
Requires-Dist: aiofiles
Requires-Dist: aiohttp
Requires-Dist: requests
Requires-Dist: types-requests
Requires-Dist: tqdm
Requires-Dist: types-tqdm
